[
  {
    "cluster_id": "6",
    "instagram": {
      "cluster_id": "6",
      "signal": "bullish",
      "slides": [
        {
          "slide_num": 1,
          "title": "호조 시그널",
          "body": "🟢 호재 시그널: Costco의 실적은 기대치를 충족하며 투자자들에게 긍정적 반응 예상",
          "signal_emoji": "🟢"
        },
        {
          "slide_num": 2,
          "title": "주요 투자 포인트",
          "body": "핵심 지표 준수: Costco의 주요 성과 지표가 기대치를 충족함으로써 투자자 신뢰 강화",
          "sectors": [
            "대형 소매",
            "할인점"
          ]
        },
        {
          "slide_num": 3,
          "title": "주의사항",
          "body": "프리미엄 평가: 높은 주가로 인해 추가적인 상승 여지 제한적",
          "sectors": [
            "증권주",
            "투자상품"
          ]
        },
        {
          "slide_num": 4,
          "title": "시장 동향 주의",
          "body": "소형주 리스크: 경제 데이터 발표 앞두고 소형주에 대한 비관적 전망 증가",
          "sectors": [
            "Russell 2000",
            "소형주"
          ],
          "caution": "투자자들은 시장 변동성에 대비해야 합니다."
        },
        {
          "slide_num": 5,
          "title": "오늘의 요약",
          "body": "Costco의 핵심 지표 준수는 긍정적이나, 높은 주가와 소형주 시장의 우려는 주의 필요.",
          "cta": "더 자세한 분석 확인: 프로필 링크"
        }
      ],
      "hashtags": [
        "#경제뉴스",
        "#투자전략",
        "#Costco",
        "#투자자정보",
        "#주식시장",
        "#경제분석",
        "#투자주의",
        "#증권정보",
        "#경제동향",
        "#투자팁"
      ],
      "disclaimer": "본 콘텐츠는 AI 분석 정보이며 투자 권유가 아닙니다"
    },
    "shorts": {
      "cluster_id": "6",
      "narration": "안녕하세요, 시그널피드입니다. 오늘의 경제 뉴스 요약입니다. 주요 이슈는 사이버 주식 시장에서 경쟁사의 실적 발표에 따른 하락입니다. 특히, Costco의 최근 분기 실적은 기대에 미치지 못했지만, 핵심 지표에서는 성과를 보여주며 투자자들의 주의가 집중되고 있습니다. Costco는 올해 강세를 보였으나, 높은 평가 가치 때문에 작은 오차에도 영향을 크게 받을 수 있는 상황입니다. 한편, 소형주 시장인 러셀 2000은 경제 지표 발표를 앞두고 투자자들 사이에서 비관적인 전망이 우세합니다. 이는 과거 한 해 동안 큰 상승세에도 불구하고, 시장의 불확실성으로 인한 것입니다. 시그널 분석 결과, 현재 시장 분위기는 조심스럽게 접근해야 함을 시사합니다. 본 콘텐츠는 AI 분석 정보이며 투자 권유가 아닙니다. 함께 성장하는 투자 여정을 위해 구독과 좋아요 부탁드립니다.",
      "duration_estimate": 60,
      "title": "사이버 주식 시장 동향과 Costco 실적 분석",
      "description": "경쟁사 실적 발표에 따른 사이버 주식 시장 동향과 Costco의 실적 분석을 통해 현재 투자 환경을 이해해보세요.",
      "tags": [
        "경제뉴스",
        "투자분석",
        "Costco",
        "소형주시장",
        "투자주의"
      ]
    }
  },
  {
    "cluster_id": "3",
    "instagram": {
      "cluster_id": "3",
      "signal": "bullish",
      "slides": [
        {
          "slide_num": 1,
          "title": "🟢 호재 시그널",
          "body": "미국 인플레이션 지표 큰 폭 상승",
          "signal_emoji": "🟢"
        },
        {
          "slide_num": 2,
          "title": "호재 섹터",
          "body": "소비재, 서비스 업종 상승 기대",
          "sectors": [
            "소비재",
            "서비스"
          ]
        },
        {
          "slide_num": 3,
          "title": "악재 고려",
          "body": "석유 가격 변동성 지속 가능성",
          "sectors": [
            "에너지",
            "운송"
          ]
        },
        {
          "slide_num": 4,
          "title": "중립 주의",
          "body": "달러 강세 장기화 가능성",
          "sectors": [
            "외환"
          ],
          "caution": "달러 강세는 수출 기업에 영향 줄 수 있음"
        },
        {
          "slide_num": 5,
          "title": "오늘의 결론",
          "body": "미국 인플레이션 상승은 긍정적 신호를 보내지만, 에너지 가격 변동과 달러 강세 등 주의해야 할 요소도 존재합니다.",
          "cta": "자세한 분석은 프로필 링크를 확인하세요!"
        }
      ],
      "hashtags": [
        "#경제뉴스",
        "#투자팁",
        "#미국경제",
        "#인플레이션",
        "#MZ투자",
        "#증권정보",
        "#글로벌경제",
        "#투자전략",
        "#시장분석",
        "#경제흐름"
      ],
      "disclaimer": "본 콘텐츠는 AI 분석 정보이며 투자 권유가 아닙니다"
    },
    "shorts": {
      "cluster_id": "3",
      "narration": "안녕하세요, 시그널피드입니다. 최근 미국의 주요 인플레이션 지표가 3년 만에 가장 큰 연간 증가를 기록했습니다. 이는 Reuters를 통해 확인되었습니다. 경제 전문가들은 이러한 인플레이션 상승이 금리 정책과 소비자 가격에 미치는 영향에 주목하고 있습니다. 특히, 이번 증가 추세는 투자자들 사이에서 긍정적인 신호로 해석되고 있으며, 이는 '매수' 경향을 반영하는 bullish 시그널로 분석됩니다. 한편, 이란의 혼란이 지속되는 가운데 에너지와 해운 분야에서도 변화가 감지되고 있습니다. 이러한 동향은 해당 섹터의 가격 변동과 공급망에 영향을 미칠 것으로 예상됩니다. 본 콘텐츠는 AI 분석 정보이며 투자 권유가 아닙니다. 투자 결정은 항상 신중하게 이루어져야 합니다. 더 많은 경제 분석을 위해 구독 부탁드립니다.",
      "duration_estimate": 60,
      "title": "인플레이션 상승과 에너지 동향",
      "description": "미국 인플레이션 지표 상승과 이란 사태에 따른 에너지 및 해운 분야의 변화 분석",
      "tags": [
        "경제 뉴스",
        "인플레이션",
        "투자 분석",
        "에너지 섹터",
        "해운 섹터"
      ]
    }
  }
]